artificial_emotion/__about__.py
artificial_emotion/__init__.py
artificial_emotion-0.1.0.dist-info/METADATA
artificial_emotion-0.1.0.dist-info/WHEEL
artificial_emotion-0.1.0.dist-info/licenses/LICENSE.rst
artificial_emotion-0.1.0.dist-info/RECORD
