Metadata-Version: 2.3
Name: artificial-emotion
Version: 0.1.0
Summary: A collection of artificial emotion functions and classes.
Project-URL: Documentation, https://artificial-emotion.readthedocs.io
Project-URL: Source, https://github.com/ojso/artificial-emotion
Project-URL: Homepage, https://github.com/ojso/artificial-emotion
Author-email: huadong <david.dong.hua@gmail.com>
License: MIT License
License-File: LICENSE.rst
Keywords: artificial,emotion
Classifier: Development Status :: 3 - Alpha
Classifier: Intended Audience :: Developers
Classifier: License :: OSI Approved :: MIT License
Classifier: Programming Language :: Python
Classifier: Programming Language :: Python :: 3
Classifier: Programming Language :: Python :: 3.10
Classifier: Programming Language :: Python :: 3.11
Classifier: Topic :: Software Development :: Build Tools
Requires-Python: >=3.10
